degenome/__init__.py
degenome/dge_to_ideogram.py
degenome/gtf_to_gen_pos.py
degenome-0.1.0.dist-info/LICENSE
degenome-0.1.0.dist-info/METADATA
degenome-0.1.0.dist-info/WHEEL
degenome-0.1.0.dist-info/top_level.txt
degenome-0.1.0.dist-info/RECORD
