Metadata-Version: 2.1
Name: degenome
Version: 0.1.0
Summary: Pipeline to convert differential gene expression matrices to Ideogram JSON
Home-page: https://github.com/eweitz/degenome
Author: Eric Weitz
Author-email: eric.m.weitz@gmail.com
License: UNKNOWN
Platform: UNKNOWN
Classifier: Development Status :: 4 - Beta
Classifier: License :: CC0 1.0 Universal (CC0 1.0) Public Domain Dedication
Classifier: Topic :: Scientific/Engineering :: Bio-Informatics
Classifier: Topic :: Scientific/Engineering :: Visualization
